fixms/__init__.py
fixms/data/RACS_1313-72.SB57526.split.ms.zip
fixms/data/SB60933.RACS_1727+37.split.ms.zip
fixms/data/__init__.py
fixms/fix_ms.py
fixms/fix_ms_corrs.py
fixms/fix_ms_dir.py
fixms/logger.py
fixms-0.4.1.dist-info/LICENSE
fixms-0.4.1.dist-info/METADATA
fixms-0.4.1.dist-info/WHEEL
fixms-0.4.1.dist-info/entry_points.txt
fixms-0.4.1.dist-info/RECORD
