Metadata-Version: 2.3
Name: fixms
Version: 0.4.1
Summary: 
License: MIT
Author: Alec Thomson (S&A, Kensington WA)
Author-email: alec.thomson@csiro.au
Requires-Python: >=3.10
Classifier: License :: OSI Approved :: MIT License
Classifier: Programming Language :: Python :: 3
Classifier: Programming Language :: Python :: 3.10
Classifier: Programming Language :: Python :: 3.11
Classifier: Programming Language :: Python :: 3.12
Classifier: Programming Language :: Python :: 3.13
Provides-Extra: dev
Provides-Extra: docs
Requires-Dist: astropy (>=6)
Requires-Dist: numpy (>=2)
Requires-Dist: python-casacore
Requires-Dist: tqdm
